local_launch/__init__.py
local_launch/banner.py
local_launch/cluster_manager.py
local_launch/command_runner.py
local_launch/config_actions.py
local_launch/dependency_checker.py
local_launch/deployer.py
local_launch/docker_manager.py
local_launch/kafka_runner.py
local_launch/local_launch.py
local_launch/logo.py
local_launch/menu.py
local_launch/progress.py
local_launch/utils.py
local_launch/config/config.toml
local_launch/config/kafka-compose.yaml
local_launch/config/kind-config.yaml
local_launch-0.1.1.dist-info/METADATA
local_launch-0.1.1.dist-info/WHEEL
local_launch-0.1.1.dist-info/top_level.txt
local_launch-0.1.1.dist-info/RECORD
